{
    "publishers": [
        "Aspatore Books"
    ],
    "subtitle": "The Restaurant Business - Industry Leaders Offer up a Behind the Scenes Glimpse into the Dynamic World of Food Service (Inside the Minds)",
    "weight": "6.4 ounces",
    "covers": [
        1959275
    ],
    "physical_format": "Paperback",
    "key": "/books/OL9878727M",
    "authors": [
        {
            "key": "/authors/OL3109343A"
        }
    ],
    "subjects": [
        "Industries - Hospitality, Travel & Tourism",
        "Business & Economics",
        "Business / Economics / Finance",
        "Business/Economics",
        "Reference - General"
    ],
    "languages": [
        {
            "key": "/languages/eng"
        }
    ],
    "first_sentence": {
        "type": "/type/text",
        "value": "In this environment, you have to throw away your watch."
    },
    "title": "Inside the Minds",
    "number_of_pages": 120,
    "isbn_13": [
        "9781587622601"
    ],
    "isbn_10": [
        "1587622602"
    ],
    "publish_date": "March 2004",
    "oclc_numbers": [
        "55750276"
    ],
    "works": [
        {
            "key": "/works/OL8963653W"
        }
    ],
    "type": {
        "key": "/type/edition"
    },
    "physical_dimensions": "8.3 x 5.4 x 0.3 inches",
    "ocaid": "insidemindsresta0000unse",
    "lc_classifications": [
        "TX911.3.M27 I58 2004"
    ],
    "source_records": [
        "ia:insidemindsresta0000unse",
        "promise:bwb_daily_pallets_2022-04-01"
    ],
    "local_id": [
        "urn:bwbsku:UR-458-255"
    ],
    "latest_revision": 6,
    "revision": 6,
    "created": {
        "type": "/type/datetime",
        "value": "2008-04-30T09:38:13.731961"
    },
    "last_modified": {
        "type": "/type/datetime",
        "value": "2023-01-14T08:20:19.792157"
    }
}